hass_brightsky_client/__init__.py
hass_brightsky_client-0.1.2.dist-info/LICENSE
hass_brightsky_client-0.1.2.dist-info/WHEEL
hass_brightsky_client-0.1.2.dist-info/METADATA
hass_brightsky_client-0.1.2.dist-info/RECORD
